example/image_analytic.py
example/periodic_image_analytic.py
nodeflux/cloud/auth/__init__.py
nodeflux/cloud/auth/credentials.py
nodeflux/cloud/auth/signer.py
nodeflux/cloud/clients/__init__.py
nodeflux/cloud/clients/image_analytic_client.py
nodeflux/cloud/requests/__init__.py
nodeflux/cloud/requests/image_analytic_request.py
nodeflux/cloud/requests/types.py
nodeflux/cloud/transports/__init__.py
nodeflux/cloud/transports/grpc_auth.py
nodeflux/cloud/transports/image_analytic_grpc_transport.py
nodeflux/cloud/utils/environment_vars.py
nodeflux/cloud/utils/exceptions.py
tests/cloud/auth/__init__.py
tests/cloud/auth/test_credentials.py
tests/cloud/auth/test_signer.py
nodeflux_cloud-0.2.2.dist-info/METADATA
nodeflux_cloud-0.2.2.dist-info/WHEEL
nodeflux_cloud-0.2.2.dist-info/top_level.txt
nodeflux_cloud-0.2.2.dist-info/RECORD
