Metadata-Version: 2.1
Name: nodeflux-cloud
Version: 0.2.2
Summary: Nodeflux Cloud Client Library for Python.
Home-page: https://gitlab.com/nodefluxio/nodeflux-cloud-python
Author: Nodeflux
Author-email: ilham@nodeflux.io
License: MIT
Platform: UNKNOWN
Classifier: License :: OSI Approved :: Apache Software License
Classifier: Programming Language :: Python
Classifier: Programming Language :: Python :: 3
Classifier: Programming Language :: Python :: 3.4
Requires-Python: >=3.4.0
Requires-Dist: pyyaml
Requires-Dist: googleapis-common-protos
Requires-Dist: grpcio
Requires-Dist: nodefluxapis (<0.3.0,>=0.2.0)
